Workbook

Sheet Dashboard
A1: Event 1 – Get Hire-Ready Day
A2: Amity University Patna • Sat 28 Nov 2026 • Tracker workbook (updates automatically from the other tabs)
A4: Event date | B4: =DATE(2026,11,28) | D4: Change here if the date moves
A5: Days to go | B5: =MAX(0,B4-TODAY())
A7: TASKS | B7: Done | C7: Total
A8: Tasks done | B8: =COUNTIF(Tasks!F:F,"Done") | C8: =COUNTA(Tasks!B5:B200)
A9: Tasks progress | B9: =IFERROR(B8/C8,0)
A10: Tasks overdue (not done, due date passed) | B10: =SUMPRODUCT((Tasks!E5:E200<TODAY())*(Tasks!E5:E200<>"")*(Tasks!F5:F200<>"Done")) | D10: Check the Tasks tab
A12: PARTNERS | B12: Confirmed | C12: Target
A13: Hiring companies confirmed | B13: =COUNTIFS(Partners!A:A,"Company",Partners!I:I,"Confirmed") | C13: 3 | D13: Target 2–3
A14: Platform partner confirmed (GfG / Unstop) | B14: =COUNTIFS(Partners!A:A,"Platform",Partners!I:I,"Confirmed") | C14: 1
A15: Alumni / HR volunteers confirmed | B15: =COUNTIFS(Partners!A:A,"Alumni / HR",Partners!I:I,"Confirmed") | C15: 6 | D15: Target 5–8
A16: Speaker confirmed | B16: =COUNTIFS(Partners!A:A,"Speaker",Partners!I:I,"Confirmed") | C16: 1
A18: REGISTRATIONS | B18: Actual | C18: Target
A19: Total registrations | B19: =Registrations!H14 | C19: 100
A20: Registrations vs target | B20: =IFERROR(B19/C19,0)
A22: BUDGET (₹) | B22: Amount
A23: Planned (max) | B23: =Budget!C11
A24: Spent so far | B24: =Budget!D11
A25: Sponsor money received | B25: =Budget!C17 | D25: Target ₹5,000+
A26: Net cost to Amity | B26: =B24-B25
A29: How to use: fill the yellow cells on each tab. Blue text = typed input, black = formula. Status columns have drop-down lists. Grey rows are examples – overwrite or delete them.

Sheet Tasks
A1: Tasks
A2: Week-by-week task list from the Event 1 plan. Update Owner, Due date and Status.
A3: Red due date = overdue. Add new tasks at the bottom.
A4: Week of | B4: Task | C4: Area | D4: Owner | E4: Due date | F4: Status | G4: Notes
A5: 46307 | B5: Send approval note to management | C5: Approvals | E5: 46311 | F5: Not started
A6: 46307 | B6: Check 28 Nov against exam calendar and Chhath (around 15 Nov) | C6: Approvals | E6: 46309 | F6: Not started
A7: 46307 | B7: Book 2 labs, seminar hall and 3 rooms | C7: Logistics | E7: 46311 | F7: Not started
A8: 46314 | B8: Form core team and fill the Team tab | C8: Team | E8: 46316 | F8: Not started
A9: 46314 | B9: List 15 companies and 15 alumni in the Partners tab | C9: Partners | E9: 46318 | F9: Not started
A10: 46314 | B10: Email GeeksforGeeks and Unstop campus teams | C10: Partners | E10: 46317 | F10: Not started
A11: 46314 | B11: Shortlist 3 speakers | C11: Partners | E11: 46318 | F11: Not started
A12: 46321 | B12: Send invites to companies and alumni | C12: Partners | E12: 46323 | F12: Not started
A13: 46321 | B13: Pick contest platform | C13: Technical | E13: 46325 | F13: Not started
A14: 46321 | B14: Draft 3 idea-pitch problem statements | C14: Technical | E14: 46325 | F14: Not started
A15: 46321 | B15: Design poster and registration form (with CV upload) | C15: Marketing | E15: 46325 | F15: Not started
A16: 46328 | B16: Open registration | C16: Marketing | E16: 46328 | F16: Not started
... A34: 46363 | B34: Fill Results tab; send results sheet + Event 2 request to management | C34: Approvals | E34: 46365 | F34: Not started

Sheet Team
A1: Team
A2: Fill names and contacts. Grey row = example.
A4: Role | B4: People needed | C4: Name(s) | D4: Phone | E4: Email | F4: Main jobs
A5: Example: Marketing | B5: 2 | C5: Riya Kumari, Aman Singh | D5: 98XXXXXXXX | E5: riya@example.com | F5: Posters, reels, ambassadors
A6: Faculty convener | B6: 1 | F6: Approval, faculty judges, final calls
A7: T&P officer | B7: 1 | F7: Company contacts, CV clinic, interview follow-up
A8: Student lead | B8: 1 | F8: Runs the team, daily check-ins, timeline
A9: Company & partner relations | B9: 2 | F9: Companies, GfG/Unstop, alumni, speaker
A10: Technical lead | B10: 2 | F10: Contest platform, problems, labs, scoring
A11: Marketing | B11: 2 | F11: Posters, reels, class ambassadors, WhatsApp
A12: Logistics & hospitality | B12: 3 | F12: Rooms, food, certificates, registration desk
A13: Volunteers (event day) | B13: 10 | F13: Desk, labs, guiding guests, photos
A14: Total people | B14: =SUM(B6:B13)

Sheet Partners
A1: Partners & outreach
A2: Companies, platform, alumni/HR volunteers and speaker. Status drives the Dashboard counts.
A4: Type | B4: Organisation / person | C4: Contact person | D4: Phone / email | E4: What we ask | F4: Date contacted | G4: Follow-up date | H4: Owner | I4: Status | J4: Notes
A5: Example | B5: ABC Technologies, Patna | C5: HR Manager | D5: hr@example.com | E5: HR judge + interview top 5 | F5: 46323 | G5: 46330 | H5: Aman | I5: Interested | J5: Call back Monday
A6: Platform | B6: GeeksforGeeks | C6: Campus team | E6: Co-host: platform, co-branded certificates, promotion | I6: Not contacted
A7: Platform | B7: Unstop | C7: Campus team | E7: Co-host: listing, certificates, promotion | I7: Not contacted
A8: Company | E8: HR/tech judge; interview top 5; CV pack | I8: Not contacted
A9: Company | E9: HR/tech judge; interview top 5; CV pack | I9: Not contacted
A10: Company | E10: HR/tech judge; interview top 5; CV pack | I10: Not contacted
A11: Company | E11: HR/tech judge; interview top 5; CV pack | I11: Not contacted
A12: Company | E12: HR/tech judge; interview top 5; CV pack | I12: Not contacted
A13: Company | E13: HR/tech judge; interview top 5; CV pack | I13: Not contacted
A14: Company | E14: HR/tech judge; interview top 5; CV pack | I14: Not contacted
A15: Company | E15: HR/tech judge; interview top 5; CV pack | I15: Not contacted
A16: Company | E16: HR/tech judge; interview top 5; CV pack | I16: Not contacted
A17: Company | E17: HR/tech judge; interview top 5; CV pack | I17: Not contacted
A18: Company | E18: HR/tech judge; interview top 5; CV pack | I18: Not contacted
A19: Company | E19: HR/tech judge; interview top 5; CV pack | I19: Not contacted
... A35: Speaker | E35: 30–45 min talk: what companies look for in freshers | I35: Not contacted

Sheet Budget
A1: Budget (₹)
A2: Plan ranges are estimates from the Event 1 plan. Enter actual spend as bills come in.
A4: Item | B4: Planned min | C4: Planned max | D4: Actual spent | E4: Paid by | F4: Notes
A5: Snacks, lunch boxes and tea (100–120 people) | B5: 5000 | C5: 7000 | F5: Ask canteen for bulk rate
A6: Prizes and goodies | B6: 2000 | C6: 3000 | F6: Or swag from GfG/Unstop/companies
A7: Certificates and printing (posters, ID cards) | B7: 1500 | C7: 2000 | F7: E-certificates save cost
A8: Speaker memento / travel | B8: 1000 | C8: 2000 | F8: Lower if speaker is local or online
A9: Miscellaneous (stationery, banners) | B9: 500 | C9: 1000
A10: (add item)
A11: Total | B11: =SUM(B5:B10) | C11: =SUM(C5:C10) | D11: =SUM(D5:D10)
A13: SPONSOR INCOME
A14: Sponsor | B14: Type (cash / in kind) | C14: Amount received (₹)
A17: Total sponsor money | C17: =SUM(C15:C16)
A19: Source of planned figures: Event 1 plan (Event1_Hire_Ready_Day_Plan.docx, section 7) – estimates, replace with real quotes.

Sheet Registrations
A1: Registrations
A2: Copy counts from the registration form (Google Form / platform) each day, by department and track.
A4: Department | B4: Beginner coding | C4: Advanced coding | D4: Idea pitch (people) | E4: Attended (event day) | F4: Mock interview requests | G4: CVs uploaded | H4: Total registered
A5: CSE / IT | H5: =SUM(B5:D5)
A6: BCA / MCA | H6: =SUM(B6:D6)
A7: ECE / EEE | H7: =SUM(B7:D7)
A8: Mechanical / Civil | H8: =SUM(B8:D8)
A9: Management (BBA/MBA) | H9: =SUM(B9:D9)
A10: Commerce / Other | H10: =SUM(B10:D10)
A11: Sciences | H11: =SUM(B11:D11)
A12: Other | H12: =SUM(B12:D12)
H13: =SUM(B13:D13)
A14: Total | B14: =SUM(B5:B13) | C14: =SUM(C5:C13) | D14: =SUM(D5:D13) | E14: =SUM(E5:E13) | F14: =SUM(F5:F13) | G14: =SUM(G5:G13) | H14: =SUM(H5:H13)
A16: DAILY LOG (for milestone posts)
A17: Date | B17: Total registrations | C17: Note
A18: 46329 | B18: 12 | C18: Example – day 2 after opening

Sheet Results
A1: Results sheet for management
A2: Fill after the event. Targets from the Event 1 plan. Linked cells fill automatically.
A4: Measure | B4: Target | C4: Actual | D4: Met? | E4: Notes
A5: Registrations | B5: 100 | C5: =Registrations!H14 | D5: =IF(OR(C5="",C5=0),"",IF(C5>=B5,"Yes","No"))
A6: Attended | B6: 80 | C6: =Registrations!E14 | D6: =IF(OR(C6="",C6=0),"",IF(C6>=B6,"Yes","No"))
A7: Departments represented | B7: 4 | C7: =COUNTIF(Registrations!H5:H13,">0") | D7: =IF(OR(C7="",C7=0),"",IF(C7>=B7,"Yes","No"))
A8: Companies involved | B8: 2 | C8: =COUNTIFS(Partners!A:A,"Company",Partners!I:I,"Confirmed") | D8: =IF(OR(C8="",C8=0),"",IF(C8>=B8,"Yes","No"))
A9: Internship interviews given | B9: 5 | D9: =IF(OR(C9="",C9=0),"",IF(C9>=B9,"Yes","No"))
A10: CVs reviewed | B10: 80 | D10: =IF(OR(C10="",C10=0),"",IF(C10>=B10,"Yes","No"))
A11: Mock interviews done | B11: 30 | D11: =IF(OR(C11="",C11=0),"",IF(C11>=B11,"Yes","No"))
A12: Sponsor money / in-kind (₹) | B12: 5000 | C12: =Budget!C17 | D12: =IF(OR(C12="",C12=0),"",IF(C12>=B12,"Yes","No"))
A13: Feedback score (out of 5) | B13: 4 | D13: =IF(OR(C13="",C13=0),"",IF(C13>=B13,"Yes","No"))
A14: Social media views | B14: 5000 | D14: =IF(OR(C14="",C14=0),"",IF(C14>=B14,"Yes","No"))
A15: Total cost (₹) | C15: =Budget!D11 | E15: From Budget tab
A16: Cost per participant (₹) | C16: =IFERROR(C15/C6,"") | E16: Total cost ÷ attended
A18: Also attach: photos, winners, 2–3 quotes from companies and students, what we change, and the request for Event 2 (Campus Hackathon, Sat 20 Feb 2027).
